{
    "swagger": "2.0",
    "info": {
        "description": "Coders API version 1.0",
        "title": "Coders API",
        "contact": {},
        "version": "1.0"
    },
    "host": "localhost:8080",
    "basePath": "/v1",
    "paths": {
        "/ping": {
            "get": {
                "description": "do ping",
                "consumes": [
                    "application/json"
                ],
                "produces": [
                    "application/json"
                ],
                "tags": [
                    "example"
                ],
                "summary": "ping example",
                "responses": {
                    "200": {
                        "description": "OK",
                        "schema": {
                            "$ref": "#/definitions/model.Ping"
                        }
                    },
                    "400": {
                        "description": "error",
                        "schema": {
                            "type": "string"
                        }
                    },
                    "404": {
                        "description": "not found error",
                        "schema": {
                            "type": "string"
                        }
                    },
                    "500": {
                        "description": "internal server error",
                        "schema": {
                            "type": "string"
                        }
                    }
                }
            }
        }
    },
    "definitions": {
        "model.Ping": {
            "type": "object",
            "properties": {
                "ping": {
                    "type": "string"
                }
            }
        }
    }
}